pamji_bot/__init__.py
pamji_bot/pamji_bot.py
pamji_bot-1.0.0.dist-info/METADATA
pamji_bot-1.0.0.dist-info/WHEEL
pamji_bot-1.0.0.dist-info/top_level.txt
pamji_bot-1.0.0.dist-info/RECORD
