Metadata-Version: 2.4
Name: pamji_bot
Version: 1.0.0
Summary: The pamji discor bot.
Requires-Python: >=3.9.21
Requires-Dist: discord
Requires-Dist: requests
Requires-Dist: ai_api_utils
Requires-Dist: dotenv
